MANIFEST.in
README.md
setup.cfg
setup.py
src/ofxstatement/__init__.py
src/ofxstatement/plugins/__init__.py
src/ofxstatement/plugins/bbva.py
src/ofxstatement/plugins/bbva_pdf.py
src/ofxstatement_bbva.egg-info/PKG-INFO
src/ofxstatement_bbva.egg-info/SOURCES.txt
src/ofxstatement_bbva.egg-info/dependency_links.txt
src/ofxstatement_bbva.egg-info/entry_points.txt
src/ofxstatement_bbva.egg-info/namespace_packages.txt
src/ofxstatement_bbva.egg-info/requires.txt
src/ofxstatement_bbva.egg-info/top_level.txt
src/ofxstatement_bbva.egg-info/zip-safe