Metadata-Version: 2.1
Name: ofxstatement-bbva
Version: 0.4
Summary: BBVA plugin for ofxstatement
Home-page: https://github.com/3v1n0/ofxstatement-bbva
Author: Marco Trevisan
Author-email: mail@3v1n0.net
License: GPLv3
Keywords: ofx,banking,statement,bbva,banco,BancoBilbaoVizcayaArgentaria
Classifier: Development Status :: 3 - Alpha
Classifier: Programming Language :: Python :: 3
Classifier: Natural Language :: English
Classifier: Topic :: Office/Business :: Financial :: Accounting
Classifier: Topic :: Utilities
Classifier: Environment :: Console
Classifier: Operating System :: OS Independent
Classifier: License :: OSI Approved :: GNU General Public License v3 (GPLv3)
